[
    {
        "thumb": "73bc8c2059c2a6b-240x180.jpg",
        "name": "【kiss糖果屋EP5】国风姐妹脱衣对决 激情舌吻秀",
        "url": "https://madou.club/kiss%e7%b3%96%e6%9e%9c%e5%b1%8bep5.html",
        "tag": "kiss糖果屋"
    },
    {
        "thumb": "232fcbfca8d8aa3-240x180.jpg",
        "name": "【kiss糖果屋EP4】麻豆女神其其、阿乃亲密之吻，挑战姐妹脱衣对决，猜错就趴光！",
        "url": "https://madou.club/kiss%e7%b3%96%e6%9e%9c%e5%b1%8bep4.html",
        "tag": "kiss糖果屋"
    },
    {
        "thumb": "b45fc9695871ca9-240x180.jpg",
        "name": "【kiss糖果屋EP3】最咸湿的女女热吻！麻辣女神岚岚、又又大玩成人版candy kiss 脱衣大挑战！",
        "url": "https://madou.club/kiss%e7%b3%96%e6%9e%9c%e5%b1%8bep3.html",
        "tag": "kiss糖果屋"
    },
    {
        "thumb": "68b6927be68ea1b-240x180.jpg",
        "name": "【kiss糖果屋EP2】麻豆女神女女咸湿舌吻秀，甜美新女神来袭米娜、馨馨脱衣挑战赛，猜错就趴光！",
        "url": "https://madou.club/kiss%e7%b3%96%e6%9e%9c%e5%b1%8bep2.html",
        "tag": "kiss糖果屋"
    },
    {
        "thumb": "488db7abdffdc95-240x180.jpg",
        "name": "【kiss糖果屋EP1】麻豆女神解密的吻 甜心姐妹脱衣挑战赛，猜错就扒光",
        "url": "https://madou.club/kiss%e7%b3%96%e6%9e%9c%e5%b1%8bep1.html",
        "tag": "kiss糖果屋"
    }
]